Metadata-Version: 2.1
Name: Deekshantshearlet6
Version: 0.6
Summary: A open source shearlet library created by Deekshant Kumar Saxena
Author: Deekshant Kumar Saxena
Author-email: deekshant.saxena@gmail.com
